v2_dataset/__init__.py
v2_dataset/__main__.py
v2_dataset/db.py
v2_dataset/mixins.py
v2_dataset/model/__init__.py
v2_dataset/model/__main__.py
v2_dataset/model/base.py
v2_dataset/model/core.py
v2_dataset/model/protocol.py
v2_dataset/model/sorting/__init__.py
v2_dataset/model/sorting/core.py
v2_dataset/model/sorting/embedded.py
v2_dataset/model/stimulus.py
v2_dataset/orm/__init__.py
v2_dataset/orm/mixins.py
v2_dataset/orm/types.py
v2_dataset/parsing.py
lcg_neuro_v2_dataset_orm-0.6.2.dist-info/LICENSE.txt
lcg_neuro_v2_dataset_orm-0.6.2.dist-info/WHEEL
lcg_neuro_v2_dataset_orm-0.6.2.dist-info/METADATA
lcg_neuro_v2_dataset_orm-0.6.2.dist-info/RECORD
