Metadata-Version: 2.1
Name: lcg-neuro-v2-dataset-orm
Version: 0.6.2
Summary: High resolution recordings in primate secondary visual cortex
Home-page: https://lcg.gitlab.io/neuro/v2/dataset/python-orm
Author: Pedro Asad
Author-email: pasad@lcg.ufrj.br
Requires-Python: >=3.6,<4.0
Classifier: Programming Language :: Python :: 3
Classifier: Programming Language :: Python :: 3.6
Classifier: Programming Language :: Python :: 3.7
Classifier: Programming Language :: Python :: 3.8
Requires-Dist: cached-property (>=1.5,<2.0)
Requires-Dist: click (>=7.0,<8.0)
Requires-Dist: colour (>=0.1.5,<0.2.0)
Requires-Dist: environ_config (>=18.2,<19.0)
Requires-Dist: iso8601 (>=0.1.12,<0.2.0)
Requires-Dist: lcg-neuro-compneuro (>=0.1.0,<0.2.0)
Requires-Dist: lcg-neuro-plx (>=0.3.1,<0.4.0)
Requires-Dist: marshmallow (>=2.19,<3.0)
Requires-Dist: numpy (>=1.16,<2.0)
Requires-Dist: packaging (>=19.2,<20.0)
Requires-Dist: pandas (>=0.24.2,<0.25.0)
Requires-Dist: pedroasad-attrs-patch (>=0.2.1,<0.3.0)
Requires-Dist: pint (>=0.9.0,<0.10.0)
Requires-Dist: sqlalchemy (>=1.3,<2.0)
Requires-Dist: stringcase (>=1.2,<2.0)
Requires-Dist: tqdm (>=4.32,<5.0)
Project-URL: Documentation, https://lcg.gitlab.io/neuro/v2/dataset/python-orm
Project-URL: Repository, https://gitlab.com/lcg/neuro/v2/dataset/python-orm
